{
    "raw_data": [
        {
            "robot_id": 0,
            "arm_index": 0,
            "joint_conf": [
                -3.139989678059713,
                -0.49001796663317876,
                -0.9200319051742554,
                2.9999558168598632,
                -1.5800131003009241,
                2.4600236415863037
            ],
            "base_mocap_pose": [
                [
                    -0.5840520262718201,
                    0.07995704561471939,
                    0.45549142360687256
                ],
                [
                    -0.001090461271815002,
                    -0.0002891118929255754,
                    0.028411975130438805,
                    0.9995957016944885
                ]
            ],
            "flange_mocap_pose": [
                [
                    -0.4443370997905731,
                    -0.935016930103302,
                    0.8347839713096619
                ],
                [
                    -0.14190183579921722,
                    0.3870808184146881,
                    -0.8717880249023438,
                    -0.26460903882980347
                ]
            ],
            "tool0_fk_pose": [
                [
                    -0.6529644131660461,
                    1.070745587348938,
                    1.3042376041412354
                ],
                [
                    -0.14056120812892914,
                    0.3663614094257355,
                    0.8740659952163696,
                    0.28640973567962646
                ]
            ],
            "tool0_fk_from_mocap": [
                [
                    -0.7499537467956543,
                    0.7494603991508484,
                    -1.778447151184082
                ],
                [
                    -0.5798877477645874,
                    -0.4543774127960205,
                    0.01598159223794937,
                    0.6760295033454895
                ]
            ]
        },
        {
            "robot_id": 0,
            "arm_index": 0,
            "joint_conf": [
                -3.14,
                -0.49,
                -0.92,
                3.0,
                -1.58,
                2.46
            ],
            "base_mocap_pose": [
                [
                    -0.5839494466781616,
                    0.0800439789891243,
                    0.45548760890960693
                ],
                [
                    -0.001029268023557961,
                    -0.0002603585016913712,
                    0.028419528156518936,
                    0.999595582485199
                ]
            ],
            "flange_mocap_pose": [
                [
                    -0.3703635036945343,
                    -0.9093981981277466,
                    0.8594653606414795
                ],
                [
                    -0.1056443527340889,
                    0.3938584625720978,
                    -0.897016167640686,
                    -0.17051923274993896
                ]
            ],
            "tool0_fk_pose": [
                [
                    -0.6529644131660461,
                    1.070745587348938,
                    1.3042376041412354
                ],
                [
                    -0.14056120812892914,
                    0.3663614094257355,
                    0.8740659952163696,
                    0.28640973567962646
                ]
            ],
            "tool0_fk_from_mocap": [
                [
                    -0.8099240660667419,
                    0.7040858864784241,
                    -1.745548963546753
                ],
                [
                    -0.6186645030975342,
                    -0.3937024176120758,
                    0.09121188521385193,
                    0.6737456321716309
                ]
            ]
        },
        {
            "robot_id": 0,
            "arm_index": 0,
            "joint_conf": [
                -2.9305604897606807,
                -0.49,
                -0.92,
                3.0,
                -1.58,
                2.46
            ],
            "base_mocap_pose": [
                [
                    -0.5838790535926819,
                    0.08005444705486298,
                    0.45548826456069946
                ],
                [
                    -0.0013313783565536141,
                    -4.6298526285681874e-05,
                    0.028396010398864746,
                    0.9995959401130676
                ]
            ],
            "flange_mocap_pose": [
                [
                    -0.30530017614364624,
                    -0.8735214471817017,
                    0.8946512937545776
                ],
                [
                    -0.06970738619565964,
                    0.3983086049556732,
                    -0.9115990996360779,
                    -0.07401517033576965
                ]
            ],
            "tool0_fk_pose": [
                [
                    -0.6529644131660461,
                    1.070745587348938,
                    1.3042376041412354
                ],
                [
                    -0.14056120812892914,
                    0.3663614094257355,
                    0.8740659952163696,
                    0.28640973567962646
                ]
            ],
            "tool0_fk_from_mocap": [
                [
                    -0.8635042309761047,
                    0.6641505360603333,
                    -1.6976661682128906
                ],
                [
                    -0.6517542600631714,
                    -0.33026009798049927,
                    0.1659480631351471,
                    0.6622733473777771
                ]
            ]
        },
        {
            "robot_id": 0,
            "arm_index": 0,
            "joint_conf": [
                -2.721120979521361,
                -0.49,
                -0.92,
                3.0,
                -1.58,
                2.46
            ],
            "base_mocap_pose": [
                [
                    -0.5838391780853271,
                    0.08009667694568634,
                    0.4556082785129547
                ],
                [
                    -0.0011457782238721848,
                    -0.00010379181185271591,
                    0.028455978259444237,
                    0.9995943903923035
                ]
            ],
            "flange_mocap_pose": [
                [
                    -0.25210052728652954,
                    -0.8290523886680603,
                    0.938734233379364
                ],
                [
                    -0.0316067673265934,
                    0.395704984664917,
                    -0.9175534248352051,
                    0.022678492590785027
                ]
            ],
            "tool0_fk_pose": [
                [
                    -0.6529644131660461,
                    1.070745587348938,
                    1.3042376041412354
                ],
                [
                    -0.14056120812892914,
                    0.3663614094257355,
                    0.8740659952163696,
                    0.28640973567962646
                ]
            ],
            "tool0_fk_from_mocap": [
                [
                    -0.9082720875740051,
                    0.6314824223518372,
                    -1.6370060443878174
                ],
                [
                    -0.6761636137962341,
                    -0.2616240382194519,
                    0.23857741057872772,
                    0.6460931897163391
                ]
            ]
        },
        {
            "robot_id": 0,
            "arm_index": 0,
            "joint_conf": [
                -2.5116814692820415,
                -0.49,
                -0.92,
                3.0,
                -1.58,
                2.46
            ],
            "base_mocap_pose": [
                [
                    -0.5838189125061035,
                    0.08015738427639008,
                    0.455571711063385
                ],
                [
                    -0.0013074874877929688,
                    -6.631169640058943e-07,
                    0.02850227616727352,
                    0.9995929598808289
                ]
            ],
            "flange_mocap_pose": [
                [
                    -0.2130487710237503,
                    -0.7777112126350403,
                    0.9896342754364014
                ],
                [
                    0.009105967357754707,
                    0.3895297050476074,
                    -0.913178026676178,
                    0.11953914910554886
                ]
            ],
            "tool0_fk_pose": [
                [
                    -0.6529644131660461,
                    1.070745587348938,
                    1.3042376041412354
                ],
                [
                    -0.14056120812892914,
                    0.3663614094257355,
                    0.8740659952163696,
                    0.28640973567962646
                ]
            ],
            "tool0_fk_from_mocap": [
                [
                    -0.9421449303627014,
                    0.6072725653648376,
                    -1.5661661624908447
                ],
                [
                    -0.6944383978843689,
                    -0.1881687194108963,
                    0.307939350605011,
                    0.6225120425224304
                ]
            ]
        },
        {
            "robot_id": 0,
            "arm_index": 0,
            "joint_conf": [
                -2.302241959042722,
                -0.49,
                -0.92,
                3.0,
                -1.58,
                2.46
            ],
            "base_mocap_pose": [
                [
                    -0.5837786197662354,
                    0.0801776722073555,
                    0.455612450838089
                ],
                [
                    -0.0013349531218409538,
                    2.2292100766208023e-05,
                    0.02840324677526951,
                    0.9995957016944885
                ]
            ],
            "flange_mocap_pose": [
                [
                    -0.18964149057865143,
                    -0.7218494415283203,
                    1.0451676845550537
                ],
                [
                    0.04857552796602249,
                    0.37756457924842834,
                    -0.8993504047393799,
                    0.2150680273771286
                ]
            ],
            "tool0_fk_pose": [
                [
                    -0.6529644131660461,
                    1.070745587348938,
                    1.3042376041412354
                ],
                [
                    -0.14056120812892914,
                    0.3663614094257355,
                    0.8740659952163696,
                    0.28640973567962646
                ]
            ],
            "tool0_fk_from_mocap": [
                [
                    -0.9638712406158447,
                    0.592535674571991,
                    -1.48829984664917
                ],
                [
                    -0.7036463022232056,
                    -0.11330107599496841,
                    0.3746991753578186,
                    0.5929967761039734
                ]
            ]
        },
        {
            "robot_id": 0,
            "arm_index": 0,
            "joint_conf": [
                -2.0928024488034023,
                -0.49,
                -0.92,
                3.0,
                -1.58,
                2.46
            ],
            "base_mocap_pose": [
                [
                    -0.5837345719337463,
                    0.0802733451128006,
                    0.45560574531555176
                ],
                [
                    -0.001301176962442696,
                    2.355844117118977e-05,
                    0.02841619774699211,
                    0.9995953440666199
                ]
            ],
            "flange_mocap_pose": [
                [
                    -0.18325190246105194,
                    -0.663644552230835,
                    1.1030198335647583
                ],
                [
                    0.08599784225225449,
                    0.36401069164276123,
                    -0.8747109174728394,
                    0.3081904947757721
                ]
            ],
            "tool0_fk_pose": [
                [
                    -0.6529644131660461,
                    1.070745587348938,
                    1.3042376041412354
                ],
                [
                    -0.14056120812892914,
                    0.3663614094257355,
                    0.8740659952163696,
                    0.28640973567962646
                ]
            ],
            "tool0_fk_from_mocap": [
                [
                    -0.9721688032150269,
                    0.5880405306816101,
                    -1.4065289497375488
                ],
                [
                    -0.7065799832344055,
                    -0.039129726588726044,
                    0.4372325837612152,
                    0.5550148487091064
                ]
            ]
        },
        {
            "robot_id": 0,
            "arm_index": 0,
            "joint_conf": [
                -1.8833629385640829,
                -0.49,
                -0.92,
                3.0,
                -1.58,
                2.46
            ],
            "base_mocap_pose": [
                [
                    -0.5837702751159668,
                    0.0803498700261116,
                    0.4556121230125427
                ],
                [
                    -0.0013966233236715198,
                    1.5162020645220764e-05,
                    0.028426235541701317,
                    0.9995949864387512
                ]
            ],
            "flange_mocap_pose": [
                [
                    -0.19402439892292023,
                    -0.6058750748634338,
                    1.1606030464172363
                ],
                [
                    0.12428423762321472,
                    0.3454340100288391,
                    -0.8404854536056519,
                    0.39851340651512146
                ]
            ],
            "tool0_fk_pose": [
                [
                    -0.6529644131660461,
                    1.070745587348938,
                    1.3042376041412354
                ],
                [
                    -0.14056120812892914,
                    0.3663614094257355,
                    0.8740659952163696,
                    0.28640973567962646
                ]
            ],
            "tool0_fk_from_mocap": [
                [
                    -0.9668487310409546,
                    0.5940023064613342,
                    -1.3246428966522217
                ],
                [
                    -0.7014652490615845,
                    0.037557270377874374,
                    0.49496275186538696,
                    0.51141756772995
                ]
            ]
        },
        {
            "robot_id": 0,
            "arm_index": 0,
            "joint_conf": [
                -1.6739234283247633,
                -0.49,
                -0.92,
                3.0,
                -1.58,
                2.46
            ],
            "base_mocap_pose": [
                [
                    -0.5838220715522766,
                    0.08044163882732391,
                    0.4555830657482147
                ],
                [
                    -0.0015339823439717293,
                    2.8319063858361915e-06,
                    0.028432797640562057,
                    0.999594509601593
                ]
            ],
            "flange_mocap_pose": [
                [
                    -0.22165793180465698,
                    -0.5509364008903503,
                    1.215248465538025
                ],
                [
                    0.15882615745067596,
                    0.32516998052597046,
                    -0.7963858246803284,
                    0.48457029461860657
                ]
            ],
            "tool0_fk_pose": [
                [
                    -0.6529644131660461,
                    1.070745587348938,
                    1.3042376041412354
                ],
                [
                    -0.14056120812892914,
                    0.3663614094257355,
                    0.8740659952163696,
                    0.28640973567962646
                ]
            ],
            "tool0_fk_from_mocap": [
                [
                    -0.9478874206542969,
                    0.6101041436195374,
                    -1.2462260723114014
                ],
                [
                    0.6895862221717834,
                    -0.11127957701683044,
                    -0.5477449893951416,
                    -0.46050316095352173
                ]
            ]
        },
        {
            "robot_id": 0,
            "arm_index": 0,
            "joint_conf": [
                -1.4644839180854439,
                -0.49,
                -0.92,
                3.0,
                -1.58,
                2.46
            ],
            "base_mocap_pose": [
                [
                    -0.5838918089866638,
                    0.08051827549934387,
                    0.45552965998649597
                ],
                [
                    -0.001630193437449634,
                    -1.0017773092840798e-05,
                    0.028465820476412773,
                    0.9995934367179871
                ]
            ],
            "flange_mocap_pose": [
                [
                    -0.2647201120853424,
                    -0.5014370083808899,
                    1.2648241519927979
                ],
                [
                    0.19197584688663483,
                    0.2993212044239044,
                    -0.7452260255813599,
                    0.5640835165977478
                ]
            ],
            "tool0_fk_pose": [
                [
                    -0.6529644131660461,
                    1.070745587348938,
                    1.3042376041412354
                ],
                [
                    -0.14056120812892914,
                    0.3663614094257355,
                    0.8740659952163696,
                    0.28640973567962646
                ]
            ],
            "tool0_fk_from_mocap": [
                [
                    -0.9164918661117554,
                    0.6357678771018982,
                    -1.1746859550476074
                ],
                [
                    0.6689205765724182,
                    -0.18397963047027588,
                    -0.5940806865692139,
                    -0.4071423411369324
                ]
            ]
        },
        {
            "robot_id": 0,
            "arm_index": 0,
            "joint_conf": [
                -1.2550444078461243,
                -0.49,
                -0.92,
                3.0,
                -1.58,
                2.46
            ],
            "base_mocap_pose": [
                [
                    -0.5839637517929077,
                    0.0806017518043518,
                    0.4554893970489502
                ],
                [
                    -0.0017301389016211033,
                    -5.9007950767409056e-05,
                    0.02845819480717182,
                    0.9995935559272766
                ]
            ],
            "flange_mocap_pose": [
                [
                    -0.3215049207210541,
                    -0.4593229591846466,
                    1.3072115182876587
                ],
                [
                    0.22513240575790405,
                    0.2706226706504822,
                    -0.6855621933937073,
                    0.6372466683387756
                ]
            ],
            "tool0_fk_pose": [
                [
                    -0.6529644131660461,
                    1.070745587348938,
                    1.3042376041412354
                ],
                [
                    -0.14056120812892914,
                    0.3663614094257355,
                    0.8740659952163696,
                    0.28640973567962646
                ]
            ],
            "tool0_fk_from_mocap": [
                [
                    -0.8738295435905457,
                    0.6698817610740662,
                    -1.1129529476165771
                ],
                [
                    0.6417578458786011,
                    -0.25637078285217285,
                    -0.6328284740447998,
                    -0.349212110042572
                ]
            ]
        },
        {
            "robot_id": 0,
            "arm_index": 0,
            "joint_conf": [
                -1.0456048976068049,
                -0.49,
                -0.92,
                3.0,
                -1.58,
                2.46
            ],
            "base_mocap_pose": [
                [
                    -0.5840294361114502,
                    0.08061739057302475,
                    0.4554682970046997
                ],
                [
                    -0.0017794579034671187,
                    -0.0001675411913311109,
                    0.02835868112742901,
                    0.9995962977409363
                ]
            ],
            "flange_mocap_pose": [
                [
                    -0.3895859122276306,
                    -0.4266260862350464,
                    1.3403326272964478
                ],
                [
                    0.2557379901409149,
                    0.23961031436920166,
                    -0.6174553036689758,
                    0.7042257189750671
                ]
            ],
            "tool0_fk_pose": [
                [
                    -0.6529644131660461,
                    1.070745587348938,
                    1.3042376041412354
                ],
                [
                    -0.14056120812892914,
                    0.3663614094257355,
                    0.8740659952163696,
                    0.28640973567962646
                ]
            ],
            "tool0_fk_from_mocap": [
                [
                    -0.8216942548751831,
                    0.7109706997871399,
                    -1.0640170574188232
                ],
                [
                    -0.6078796982765198,
                    0.32611605525016785,
                    0.665012538433075,
                    0.28616246581077576
                ]
            ]
        },
        {
            "robot_id": 0,
            "arm_index": 0,
            "joint_conf": [
                -0.8361653873674855,
                -0.49,
                -0.92,
                3.0,
                -1.58,
                2.46
            ],
            "base_mocap_pose": [
                [
                    -0.584160566329956,
                    0.08067432790994644,
                    0.4554303288459778
                ],
                [
                    -0.0018345573917031288,
                    -0.00024635475710965693,
                    0.028385698795318604,
                    0.9995953440666199
                ]
            ],
            "flange_mocap_pose": [
                [
                    -0.46578705310821533,
                    -0.4045986831188202,
                    1.3628231287002563
                ],
                [
                    0.28206926584243774,
                    0.20598220825195312,
                    -0.5418826937675476,
                    0.7644419074058533
                ]
            ],
            "tool0_fk_pose": [
                [
                    -0.6529644131660461,
                    1.070745587348938,
                    1.3042376041412354
                ],
                [
                    -0.14056120812892914,
                    0.3663614094257355,
                    0.8740659952163696,
                    0.28640973567962646
                ]
            ],
            "tool0_fk_from_mocap": [
                [
                    -0.7624919414520264,
                    0.7570640444755554,
                    -1.029839038848877
                ],
                [
                    -0.5668053030967712,
                    0.39144620299339294,
                    0.6910806894302368,
                    0.218881756067276
                ]
            ]
        },
        {
            "robot_id": 0,
            "arm_index": 0,
            "joint_conf": [
                -0.6267258771281656,
                -0.49,
                -0.92,
                3.0,
                -1.58,
                2.46
            ],
            "base_mocap_pose": [
                [
                    -0.5842931866645813,
                    0.08068714290857315,
                    0.4554024040699005
                ],
                [
                    -0.001805944717489183,
                    -0.00037641351809725165,
                    0.028423281386494637,
                    0.9995942711830139
                ]
            ],
            "flange_mocap_pose": [
                [
                    -0.5468182563781738,
                    -0.3944871127605438,
                    1.3735997676849365
                ],
                [
                    0.3050422668457031,
                    0.1701064109802246,
                    -0.4603983461856842,
                    0.8161166310310364
                ]
            ],
            "tool0_fk_pose": [
                [
                    -0.6529644131660461,
                    1.070745587348938,
                    1.3042376041412354
                ],
                [
                    -0.14056120812892914,
                    0.3663614094257355,
                    0.8740659952163696,
                    0.28640973567962646
                ]
            ],
            "tool0_fk_from_mocap": [
                [
                    -0.6988450884819031,
                    0.8062763810157776,
                    -1.0121853351593018
                ],
                [
                    -0.5194377899169922,
                    0.4521864056587219,
                    0.7095363140106201,
                    0.14923150837421417
                ]
            ]
        },
        {
            "robot_id": 0,
            "arm_index": 0,
            "joint_conf": [
                -0.4172863668888458,
                -0.49,
                -0.92,
                3.0,
                -1.58,
                2.46
            ],
            "base_mocap_pose": [
                [
                    -0.5843968987464905,
                    0.08069692552089691,
                    0.45536959171295166
                ],
                [
                    -0.0018232582369819283,
                    -0.0005978202680125833,
                    0.028409307822585106,
                    0.9995946288108826
                ]
            ],
            "flange_mocap_pose": [
                [
                    -0.6292783617973328,
                    -0.39654427766799927,
                    1.3721911907196045
                ],
                [
                    0.3239761292934418,
                    0.13170699775218964,
                    -0.3752117156982422,
                    0.8584339618682861
                ]
            ],
            "tool0_fk_pose": [
                [
                    -0.6529644131660461,
                    1.070745587348938,
                    1.3042376041412354
                ],
                [
                    -0.14056120812892914,
                    0.3663614094257355,
                    0.8740659952163696,
                    0.28640973567962646
                ]
            ],
            "tool0_fk_from_mocap": [
                [
                    -0.6333482265472412,
                    0.856434166431427,
                    -1.011686086654663
                ],
                [
                    -0.4660361409187317,
                    0.5072111487388611,
                    0.7205870151519775,
                    0.07938214391469955
                ]
            ]
        },
        {
            "robot_id": 0,
            "arm_index": 0,
            "joint_conf": [
                -0.2078468566495264,
                -0.49,
                -0.92,
                3.0,
                -1.58,
                2.46
            ],
            "base_mocap_pose": [
                [
                    -0.5845282077789307,
                    0.08068031072616577,
                    0.4553561806678772
                ],
                [
                    -0.0017937879310920835,
                    -0.0007341522723436356,
                    0.02835732325911522,
                    0.9995960593223572
                ]
            ],
            "flange_mocap_pose": [
                [
                    -0.7094729542732239,
                    -0.41064587235450745,
                    1.3587946891784668
                ],
                [
                    0.3417802155017853,
                    0.09240293502807617,
                    -0.2851516306400299,
                    0.8906943798065186
                ]
            ],
            "tool0_fk_pose": [
                [
                    -0.6529644131660461,
                    1.070745587348938,
                    1.3042376041412354
                ],
                [
                    -0.14056120812892914,
                    0.3663614094257355,
                    0.8740659952163696,
                    0.28640973567962646
                ]
            ],
            "tool0_fk_from_mocap": [
                [
                    -0.5689841508865356,
                    0.9053471684455872,
                    -1.0282479524612427
                ],
                [
                    -0.4083210527896881,
                    0.5585080981254578,
                    0.721992552280426,
                    0.008326036855578423
                ]
            ]
        },
        {
            "robot_id": 0,
            "arm_index": 0,
            "joint_conf": [
                0.0015926535897929917,
                -0.49,
                -0.92,
                3.0,
                -1.58,
                2.46
            ],
            "base_mocap_pose": [
                [
                    -0.5846692323684692,
                    0.0806904286146164,
                    0.45528584718704224
                ],
                [
                    -0.0016678378451615572,
                    -0.00077911646803841,
                    0.02841438353061676,
                    0.999594509601593
                ]
            ],
            "flange_mocap_pose": [
                [
                    -0.7838245034217834,
                    -0.4363281726837158,
                    1.333885908126831
                ],
                [
                    0.35336485505104065,
                    0.05044084042310715,
                    -0.1928669959306717,
                    0.9139974117279053
                ]
            ],
            "tool0_fk_pose": [
                [
                    -0.6529644131660461,
                    1.070745587348938,
                    1.3042376041412354
                ],
                [
                    -0.14056120812892914,
                    0.3663614094257355,
                    0.8740659952163696,
                    0.28640973567962646
                ]
            ],
            "tool0_fk_from_mocap": [
                [
                    -0.5086345076560974,
                    0.9508586525917053,
                    -1.0613356828689575
                ],
                [
                    -0.3444273769855499,
                    0.6021612286567688,
                    0.7175837755203247,
                    -0.06200947239995003
                ]
            ]
        },
        {
            "robot_id": 0,
            "arm_index": 0,
            "joint_conf": [
                0.21103216382911238,
                -0.49,
                -0.92,
                3.0,
                -1.58,
                2.46
            ],
            "base_mocap_pose": [
                [
                    -0.5847832560539246,
                    0.08066365867853165,
                    0.4552685618400574
                ],
                [
                    -0.0016407596413046122,
                    -0.0008663084590807557,
                    0.028457168489694595,
                    0.9995933175086975
                ]
            ],
            "flange_mocap_pose": [
                [
                    -0.8491874933242798,
                    -0.47239208221435547,
                    1.2986854314804077
                ],
                [
                    0.36176979541778564,
                    0.008989048190414906,
                    -0.09850621223449707,
                    0.9270050525665283
                ]
            ],
            "tool0_fk_pose": [
                [
                    -0.6529644131660461,
                    1.070745587348938,
                    1.3042376041412354
                ],
                [
                    -0.14056120812892914,
                    0.3663614094257355,
                    0.8740659952163696,
                    0.28640973567962646
                ]
            ],
            "tool0_fk_from_mocap": [
                [
                    -0.45488354563713074,
                    0.991072952747345,
                    -1.1093528270721436
                ],
                [
                    -0.27786120772361755,
                    0.6394088268280029,
                    0.7046747207641602,
                    -0.13184474408626556
                ]
            ]
        },
        {
            "robot_id": 0,
            "arm_index": 0,
            "joint_conf": [
                0.4204716740684318,
                -0.49,
                -0.92,
                3.0,
                -1.58,
                2.46
            ],
            "base_mocap_pose": [
                [
                    -0.5848916172981262,
                    0.08067306876182556,
                    0.4552001953125
                ],
                [
                    -0.0013884512009099126,
                    -0.0009173398721031845,
                    0.02848120406270027,
                    0.9995929598808289
                ]
            ],
            "flange_mocap_pose": [
                [
                    -0.9024918675422668,
                    -0.5172668099403381,
                    1.2545188665390015
                ],
                [
                    0.36633074283599854,
                    -0.03285559266805649,
                    -0.0018422662978991866,
                    0.9299026131629944
                ]
            ],
            "tool0_fk_pose": [
                [
                    -0.6529644131660461,
                    1.070745587348938,
                    1.3042376041412354
                ],
                [
                    -0.14056120812892914,
                    0.3663614094257355,
                    0.8740659952163696,
                    0.28640973567962646
                ]
            ],
            "tool0_fk_from_mocap": [
                [
                    -0.4101554751396179,
                    1.0239875316619873,
                    -1.1703596115112305
                ],
                [
                    -0.2075859010219574,
                    0.6700289249420166,
                    0.6837326884269714,
                    -0.20119398832321167
                ]
            ]
        },
        {
            "robot_id": 0,
            "arm_index": 0,
            "joint_conf": [
                0.6299111843077516,
                -0.49,
                -0.92,
                3.0,
                -1.58,
                2.46
            ],
            "base_mocap_pose": [
                [
                    -0.5849981904029846,
                    0.0805085077881813,
                    0.4552009403705597
                ],
                [
                    -0.0015833304496482015,
                    -0.0009328078012913465,
                    0.02831296995282173,
                    0.9995974898338318
                ]
            ],
            "flange_mocap_pose": [
                [
                    -0.9415230751037598,
                    -0.5688725113868713,
                    1.2035305500030518
                ],
                [
                    0.3694251477718353,
                    -0.07222650945186615,
                    0.09494910389184952,
                    0.9215709567070007
                ]
            ],
            "tool0_fk_pose": [
                [
                    -0.6529644131660461,
                    1.070745587348938,
                    1.3042376041412354
                ],
                [
                    -0.14056120812892914,
                    0.3663614094257355,
                    0.8740659952163696,
                    0.28640973567962646
                ]
            ],
            "tool0_fk_from_mocap": [
                [
                    -0.37636399269104004,
                    1.048285722732544,
                    -1.2414519786834717
                ],
                [
                    -0.1374276578426361,
                    0.694562554359436,
                    0.6531285643577576,
                    -0.2685508131980896
                ]
            ]
        },
        {
            "robot_id": 0,
            "arm_index": 0,
            "joint_conf": [
                0.839350694547071,
                -0.49,
                -0.92,
                3.0,
                -1.58,
                2.46
            ],
            "base_mocap_pose": [
                [
                    -0.5850253701210022,
                    0.08040926605463028,
                    0.45522361993789673
                ],
                [
                    -0.0014452827163040638,
                    -0.0010577230714261532,
                    0.028245514258742332,
                    0.9995993971824646
                ]
            ],
            "flange_mocap_pose": [
                [
                    -0.9646974802017212,
                    -0.6250185966491699,
                    1.147922396659851
                ],
                [
                    0.3672693967819214,
                    -0.11264466494321823,
                    0.18981263041496277,
                    0.9035460948944092
                ]
            ],
            "tool0_fk_pose": [
                [
                    -0.6529644131660461,
                    1.070745587348938,
                    1.3042376041412354
                ],
                [
                    -0.14056120812892914,
                    0.3663614094257355,
                    0.8740659952163696,
                    0.28640973567962646
                ]
            ],
            "tool0_fk_from_mocap": [
                [
                    -0.35490214824676514,
                    1.0630013942718506,
                    -1.3195834159851074
                ],
                [
                    -0.06419415771961212,
                    0.7109849452972412,
                    0.6166748404502869,
                    -0.331800639629364
                ]
            ]
        },
        {
            "robot_id": 0,
            "arm_index": 0,
            "joint_conf": [
                1.0487902047863904,
                -0.49,
                -0.92,
                3.0,
                -1.58,
                2.46
            ],
            "base_mocap_pose": [
                [
                    -0.5850020051002502,
                    0.08029668033123016,
                    0.45521992444992065
                ],
                [
                    -0.0012448780471459031,
                    -0.0011389183346182108,
                    0.028166789561510086,
                    0.9996017813682556
                ]
            ],
            "flange_mocap_pose": [
                [
                    -0.9708468317985535,
                    -0.6833396553993225,
                    1.089961051940918
                ],
                [
                    0.3615017831325531,
                    -0.15109123289585114,
                    0.2821170389652252,
                    0.8757270574569702
                ]
            ],
            "tool0_fk_pose": [
                [
                    -0.6529644131660461,
                    1.070745587348938,
                    1.3042376041412354
                ],
                [
                    -0.14056120812892914,
                    0.3663614094257355,
                    0.8740659952163696,
                    0.28640973567962646
                ]
            ],
            "tool0_fk_from_mocap": [
                [
                    -0.34679239988327026,
                    1.0673563480377197,
                    -1.401522159576416
                ],
                [
                    0.008789639919996262,
                    0.7197377681732178,
                    0.573439359664917,
                    -0.3912384808063507
                ]
            ]
        },
        {
            "robot_id": 0,
            "arm_index": 0,
            "joint_conf": [
                1.2582297150257102,
                -0.49,
                -0.92,
                3.0,
                -1.58,
                2.46
            ],
            "base_mocap_pose": [
                [
                    -0.5850372314453125,
                    0.08022787421941757,
                    0.4551582932472229
                ],
                [
                    -0.0009621104109100997,
                    -0.0010123784886673093,
                    0.028175871819257736,
                    0.9996020197868347
                ]
            ],
            "flange_mocap_pose": [
                [
                    -0.9598496556282043,
                    -0.7411518096923828,
                    1.0323143005371094
                ],
                [
                    0.3504888117313385,
                    -0.1877538412809372,
                    0.37259042263031006,
                    0.8385001420974731
                ]
            ],
            "tool0_fk_pose": [
                [
                    -0.6529644131660461,
                    1.070745587348938,
                    1.3042376041412354
                ],
                [
                    -0.14056120812892914,
                    0.3663614094257355,
                    0.8740659952163696,
                    0.28640973567962646
                ]
            ],
            "tool0_fk_from_mocap": [
                [
                    -0.3522794842720032,
                    1.0612475872039795,
                    -1.483491063117981
                ],
                [
                    0.08236800134181976,
                    0.71969074010849,
                    0.5241762399673462,
                    -0.4477722942829132
                ]
            ]
        },
        {
            "robot_id": 0,
            "arm_index": 0,
            "joint_conf": [
                1.4676692252650292,
                -0.49,
                -0.92,
                3.0,
                -1.58,
                2.46
            ],
            "base_mocap_pose": [
                [
                    -0.5850094556808472,
                    0.08014509081840515,
                    0.4552263617515564
                ],
                [
                    -0.0010663485154509544,
                    -0.0010084734531119466,
                    0.028177421540021896,
                    0.9996019005775452
                ]
            ],
            "flange_mocap_pose": [
                [
                    -0.931887149810791,
                    -0.7959802150726318,
                    0.9774821400642395
                ],
                [
                    0.33581581711769104,
                    -0.2227395623922348,
                    0.4584116041660309,
                    0.7921322584152222
                ]
            ],
            "tool0_fk_pose": [
                [
                    -0.6529644131660461,
                    1.070745587348938,
                    1.3042376041412354
                ],
                [
                    -0.14056120812892914,
                    0.3663614094257355,
                    0.8740659952163696,
                    0.28640973567962646
                ]
            ],
            "tool0_fk_from_mocap": [
                [
                    -0.37137383222579956,
                    1.0447800159454346,
                    -1.5619693994522095
                ],
                [
                    0.1551094502210617,
                    0.711961567401886,
                    0.46936094760894775,
                    -0.4987505376338959
                ]
            ]
        },
        {
            "robot_id": 0,
            "arm_index": 0,
            "joint_conf": [
                1.67710873550435,
                -0.49,
                -0.92,
                3.0,
                -1.58,
                2.46
            ],
            "base_mocap_pose": [
                [
                    -0.5849314332008362,
                    0.08012041449546814,
                    0.4552612900733948
                ],
                [
                    -0.0009867027401924133,
                    -0.0009633103618398309,
                    0.028339654207229614,
                    0.9995974898338318
                ]
            ],
            "flange_mocap_pose": [
                [
                    -0.8885765671730042,
                    -0.8453977704048157,
                    0.9279063940048218
                ],
                [
                    0.3167079985141754,
                    -0.2568601667881012,
                    0.5380946397781372,
                    0.7376808524131775
                ]
            ],
            "tool0_fk_pose": [
                [
                    -0.6529644131660461,
                    1.070745587348938,
                    1.3042376041412354
                ],
                [
                    -0.14056120812892914,
                    0.3663614094257355,
                    0.8740659952163696,
                    0.28640973567962646
                ]
            ],
            "tool0_fk_from_mocap": [
                [
                    -0.40293461084365845,
                    1.0189199447631836,
                    -1.6334593296051025
                ],
                [
                    -0.2272523045539856,
                    -0.6962839961051941,
                    -0.41074129939079285,
                    0.542988657951355
                ]
            ]
        },
        {
            "robot_id": 0,
            "arm_index": 0,
            "joint_conf": [
                1.8865482457436689,
                -0.49,
                -0.92,
                3.0,
                -1.58,
                2.46
            ],
            "base_mocap_pose": [
                [
                    -0.5848409533500671,
                    0.08001434803009033,
                    0.45534875988960266
                ],
                [
                    -0.0011065870057791471,
                    -0.0009645626996643841,
                    0.028255581855773926,
                    0.9995996356010437
                ]
            ],
            "flange_mocap_pose": [
                [
                    -0.8317558765411377,
                    -0.8871003985404968,
                    0.8857772350311279
                ],
                [
                    0.2951851189136505,
                    -0.2854389548301697,
                    0.614162802696228,
                    0.6739394664764404
                ]
            ],
            "tool0_fk_pose": [
                [
                    -0.6529644131660461,
                    1.070745587348938,
                    1.3042376041412354
                ],
                [
                    -0.14056120812892914,
                    0.3663614094257355,
                    0.8740659952163696,
                    0.28640973567962646
                ]
            ],
            "tool0_fk_from_mocap": [
                [
                    -0.44557955861091614,
                    0.9846954941749573,
                    -1.694718360900879
                ],
                [
                    -0.29522445797920227,
                    -0.6729966402053833,
                    -0.3451426327228546,
                    0.5837762355804443
                ]
            ]
        },
        {
            "robot_id": 0,
            "arm_index": 0,
            "joint_conf": [
                2.0959877559829887,
                -0.49,
                -0.92,
                3.0,
                -1.58,
                2.46
            ],
            "base_mocap_pose": [
                [
                    -0.5847187042236328,
                    0.07996790111064911,
                    0.4553791880607605
                ],
                [
                    -0.001102572656236589,
                    -0.0008475367212668061,
                    0.02825518138706684,
                    0.9995997548103333
                ]
            ],
            "flange_mocap_pose": [
                [
                    -0.7637926936149597,
                    -0.919600784778595,
                    0.8528034090995789
                ],
                [
                    0.2698650062084198,
                    -0.31232815980911255,
                    0.6820886135101318,
                    0.603638231754303
                ]
            ],
            "tool0_fk_pose": [
                [
                    -0.6529644131660461,
                    1.070745587348938,
                    1.3042376041412354
                ],
                [
                    -0.14056120812892914,
                    0.3663614094257355,
                    0.8740659952163696,
                    0.28640973567962646
                ]
            ],
            "tool0_fk_from_mocap": [
                [
                    -0.4976099729537964,
                    0.943648636341095,
                    -1.7434065341949463
                ],
                [
                    -0.36074626445770264,
                    -0.6423585414886475,
                    -0.2772959768772125,
                    0.6167207956314087
                ]
            ]
        },
        {
            "robot_id": 0,
            "arm_index": 0,
            "joint_conf": [
                2.3054272662223085,
                -0.49,
                -0.92,
                3.0,
                -1.58,
                2.46
            ],
            "base_mocap_pose": [
                [
                    -0.5846092104911804,
                    0.07991214841604233,
                    0.45541781187057495
                ],
                [
                    -0.001161155174486339,
                    -0.0007039234042167664,
                    0.028288202360272408,
                    0.9995989203453064
                ]
            ],
            "flange_mocap_pose": [
                [
                    -0.6876609325408936,
                    -0.9412826299667358,
                    0.8305050730705261
                ],
                [
                    0.24159424006938934,
                    -0.3368697166442871,
                    0.741982638835907,
                    0.5268896818161011
                ]
            ],
            "tool0_fk_pose": [
                [
                    -0.6529644131660461,
                    1.070745587348938,
                    1.3042376041412354
                ],
                [
                    -0.14056120812892914,
                    0.3663614094257355,
                    0.8740659952163696,
                    0.28640973567962646
                ]
            ],
            "tool0_fk_from_mocap": [
                [
                    -0.5567071437835693,
                    0.8975086808204651,
                    -1.7771998643875122
                ],
                [
                    -0.423024982213974,
                    -0.604978084564209,
                    -0.20686529576778412,
                    0.6420733332633972
                ]
            ]
        },
        {
            "robot_id": 0,
            "arm_index": 0,
            "joint_conf": [
                2.5148667764616275,
                -0.49,
                -0.92,
                3.0,
                -1.58,
                2.46
            ],
            "base_mocap_pose": [
                [
                    -0.5844609141349792,
                    0.07992833107709885,
                    0.45544731616973877
                ],
                [
                    -0.001036260393448174,
                    -0.0006304490379989147,
                    0.028370575979351997,
                    0.9995967745780945
                ]
            ],
            "flange_mocap_pose": [
                [
                    -0.6067413091659546,
                    -0.9513222575187683,
                    0.8198958039283752
                ],
                [
                    0.21007852256298065,
                    -0.35627007484436035,
                    0.7950394749641418,
                    0.44367876648902893
                ]
            ],
            "tool0_fk_pose": [
                [
                    -0.6529644131660461,
                    1.070745587348938,
                    1.3042376041412354
                ],
                [
                    -0.14056120812892914,
                    0.3663614094257355,
                    0.8740659952163696,
                    0.28640973567962646
                ]
            ],
            "tool0_fk_from_mocap": [
                [
                    -0.6203128099441528,
                    0.8484166264533997,
                    -1.7946820259094238
                ],
                [
                    -0.48014283180236816,
                    -0.5599602460861206,
                    -0.13321058452129364,
                    0.6619384288787842
                ]
            ]
        },
        {
            "robot_id": 0,
            "arm_index": 0,
            "joint_conf": [
                2.7243062867009473,
                -0.49,
                -0.92,
                3.0,
                -1.58,
                2.46
            ],
            "base_mocap_pose": [
                [
                    -0.5843114852905273,
                    0.07991853356361389,
                    0.45547598600387573
                ],
                [
                    -0.0010135441552847624,
                    -0.0005029300809837878,
                    0.028386695310473442,
                    0.9995964169502258
                ]
            ],
            "flange_mocap_pose": [
                [
                    -0.5244954228401184,
                    -0.9492049217224121,
                    0.8212864995002747
                ],
                [
                    0.17612485587596893,
                    -0.3726060390472412,
                    0.83837890625,
                    0.35674306750297546
                ]
            ],
            "tool0_fk_pose": [
                [
                    -0.6529644131660461,
                    1.070745587348938,
                    1.3042376041412354
                ],
                [
                    -0.14056120812892914,
                    0.3663614094257355,
                    0.8740659952163696,
                    0.28640973567962646
                ]
            ],
            "tool0_fk_from_mocap": [
                [
                    -0.6856069564819336,
                    0.7983439564704895,
                    -1.795142412185669
                ],
                [
                    -0.5322438478469849,
                    -0.5092031359672546,
                    -0.059545744210481644,
                    0.6737083792686462
                ]
            ]
        },
        {
            "robot_id": 0,
            "arm_index": 0,
            "joint_conf": [
                2.9337457969402663,
                -0.49,
                -0.92,
                3.0,
                -1.58,
                2.46
            ],
            "base_mocap_pose": [
                [
                    -0.5841886401176453,
                    0.07995806634426117,
                    0.4554935097694397
                ],
                [
                    -0.001058978377841413,
                    -0.0003459305444266647,
                    0.02838529646396637,
                    0.9995964169502258
                ]
            ],
            "flange_mocap_pose": [
                [
                    -0.44462305307388306,
                    -0.9350788593292236,
                    0.8347271680831909
                ],
                [
                    0.14169111847877502,
                    -0.38681498169898987,
                    0.8719026446342468,
                    0.26473310589790344
                ]
            ],
            "tool0_fk_pose": [
                [
                    -0.6529644131660461,
                    1.070745587348938,
                    1.3042376041412354
                ],
                [
                    -0.14056120812892914,
                    0.3663614094257355,
                    0.8740659952163696,
                    0.28640973567962646
                ]
            ],
            "tool0_fk_from_mocap": [
                [
                    -0.7497246861457825,
                    0.7496364712715149,
                    -1.7785208225250244
                ],
                [
                    -0.5797404050827026,
                    -0.4541785717010498,
                    0.01586613990366459,
                    0.6762922406196594
                ]
            ]
        }
    ]
}