{
    "raw_data": [
        {
            "left_EE_pose": [
                [
                    -1.6511088609695435,
                    -0.3374556005001068,
                    0.9465675950050354
                ],
                [
                    -0.39584100246429443,
                    -0.7349370718002319,
                    0.4231163561344147,
                    0.3523491621017456
                ]
            ],
            "right_EE_pose": [
                [
                    -1.6599730253219604,
                    0.6404662728309631,
                    0.9607406258583069
                ],
                [
                    0.2400781214237213,
                    0.824281632900238,
                    -0.13369525969028473,
                    -0.49502313137054443
                ]
            ]
        },
        {
            "left_EE_pose": [
                [
                    -1.6509953737258911,
                    -0.33739402890205383,
                    0.9465643763542175
                ],
                [
                    -0.3959086835384369,
                    -0.7348188757896423,
                    0.4231858253479004,
                    0.3524361848831177
                ]
            ],
            "right_EE_pose": [
                [
                    -1.6599993705749512,
                    0.6405393481254578,
                    0.9606683254241943
                ],
                [
                    0.24003273248672485,
                    0.8243182897567749,
                    -0.13379967212677002,
                    -0.4949558675289154
                ]
            ]
        },
        {
            "left_EE_pose": [
                [
                    -1.6492098569869995,
                    -0.33585125207901,
                    0.9466061592102051
                ],
                [
                    -0.39615777134895325,
                    -0.7345491051673889,
                    0.4236697256565094,
                    0.3521372675895691
                ]
            ],
            "right_EE_pose": [
                [
                    -1.661466121673584,
                    0.6409618258476257,
                    0.9592466950416565
                ],
                [
                    0.23729124665260315,
                    0.8247208595275879,
                    -0.13587382435798645,
                    -0.49504202604293823
                ]
            ]
        },
        {
            "left_EE_pose": [
                [
                    -1.6475954055786133,
                    -0.33447763323783875,
                    0.9469177722930908
                ],
                [
                    -0.39612749218940735,
                    -0.7335897088050842,
                    0.42534345388412476,
                    0.3521535396575928
                ]
            ],
            "right_EE_pose": [
                [
                    -1.6629345417022705,
                    0.6415051221847534,
                    0.9577511548995972
                ],
                [
                    0.23626595735549927,
                    0.8246458768844604,
                    -0.1376396119594574,
                    -0.49516957998275757
                ]
            ]
        },
        {
            "left_EE_pose": [
                [
                    -1.646329641342163,
                    -0.3336392939090729,
                    0.94705730676651
                ],
                [
                    -0.39686015248298645,
                    -0.7334147095680237,
                    0.42530426383018494,
                    0.35174044966697693
                ]
            ],
            "right_EE_pose": [
                [
                    -1.6635783910751343,
                    0.6417877674102783,
                    0.9569512605667114
                ],
                [
                    0.23581814765930176,
                    0.824325442314148,
                    -0.138655424118042,
                    -0.49563297629356384
                ]
            ]
        },
        {
            "left_EE_pose": [
                [
                    -1.6440799236297607,
                    -0.33158233761787415,
                    0.9470658898353577
                ],
                [
                    -0.39657285809516907,
                    -0.7328338027000427,
                    0.4268457889556885,
                    0.3514077961444855
                ]
            ],
            "right_EE_pose": [
                [
                    -1.6657918691635132,
                    0.6425042152404785,
                    0.954876720905304
                ],
                [
                    0.23311638832092285,
                    0.8249590396881104,
                    -0.14168515801429749,
                    -0.49499961733818054
                ]
            ]
        },
        {
            "left_EE_pose": [
                [
                    -1.642202377319336,
                    -0.3304734230041504,
                    0.947470486164093
                ],
                [
                    -0.39695531129837036,
                    -0.7322781085968018,
                    0.4270491898059845,
                    0.35188665986061096
                ]
            ],
            "right_EE_pose": [
                [
                    -1.666752815246582,
                    0.6430177688598633,
                    0.9535373449325562
                ],
                [
                    0.23182973265647888,
                    0.8248916268348694,
                    -0.14299745857715607,
                    -0.4953387677669525
                ]
            ]
        },
        {
            "left_EE_pose": [
                [
                    -1.6404712200164795,
                    -0.32891517877578735,
                    0.9474911689758301
                ],
                [
                    -0.3972521424293518,
                    -0.7313266396522522,
                    0.42899224162101746,
                    0.3511662483215332
                ]
            ],
            "right_EE_pose": [
                [
                    -1.6683567762374878,
                    0.6436429023742676,
                    0.9519740343093872
                ],
                [
                    0.2301037758588791,
                    0.8246001601219177,
                    -0.1458180695772171,
                    -0.4958063066005707
                ]
            ]
        },
        {
            "left_EE_pose": [
                [
                    -1.6389799118041992,
                    -0.3278094232082367,
                    0.9476980566978455
                ],
                [
                    -0.39705196022987366,
                    -0.7315618991851807,
                    0.4291456937789917,
                    0.35071486234664917
                ]
            ],
            "right_EE_pose": [
                [
                    -1.66922128200531,
                    0.6441425681114197,
                    0.9508869647979736
                ],
                [
                    0.22913457453250885,
                    0.8245360851287842,
                    -0.14715580642223358,
                    -0.49596649408340454
                ]
            ]
        },
        {
            "left_EE_pose": [
                [
                    -1.6371432542800903,
                    -0.3264860510826111,
                    0.9477716684341431
                ],
                [
                    -0.39701056480407715,
                    -0.7306397557258606,
                    0.4306768774986267,
                    0.3508070409297943
                ]
            ],
            "right_EE_pose": [
                [
                    -1.6707406044006348,
                    0.6449088454246521,
                    0.9492289423942566
                ],
                [
                    0.2274981141090393,
                    0.824801504611969,
                    -0.14919190108776093,
                    -0.4956701099872589
                ]
            ]
        },
        {
            "left_EE_pose": [
                [
                    -1.6356061697006226,
                    -0.325065553188324,
                    0.9477033615112305
                ],
                [
                    -0.3956678807735443,
                    -0.73066246509552,
                    0.43295931816101074,
                    0.3494645655155182
                ]
            ],
            "right_EE_pose": [
                [
                    -1.6719330549240112,
                    0.6454620361328125,
                    0.9478796720504761
                ],
                [
                    0.2256915271282196,
                    0.824822723865509,
                    -0.1513821929693222,
                    -0.4957965314388275
                ]
            ]
        },
        {
            "left_EE_pose": [
                [
                    -1.6337915658950806,
                    -0.3241102695465088,
                    0.9480060935020447
                ],
                [
                    -0.3966735005378723,
                    -0.7299972772598267,
                    0.4322229027748108,
                    0.3506244122982025
                ]
            ],
            "right_EE_pose": [
                [
                    -1.6728664636611938,
                    0.646090030670166,
                    0.9465584754943848
                ],
                [
                    0.22449611127376556,
                    0.8243299126625061,
                    -0.15271933376789093,
                    -0.4967478811740875
                ]
            ]
        },
        {
            "left_EE_pose": [
                [
                    -1.632982611656189,
                    -0.3235131800174713,
                    0.9480148553848267
                ],
                [
                    -0.39643141627311707,
                    -0.7296379208564758,
                    0.4331691861152649,
                    0.3504784107208252
                ]
            ],
            "right_EE_pose": [
                [
                    -1.673561453819275,
                    0.6464259624481201,
                    0.945827066898346
                ],
                [
                    0.2241205871105194,
                    0.824617326259613,
                    -0.15374988317489624,
                    -0.4961221218109131
                ]
            ]
        },
        {
            "left_EE_pose": [
                [
                    -1.630450963973999,
                    -0.3217979073524475,
                    0.9483978748321533
                ],
                [
                    -0.39577430486679077,
                    -0.7294156551361084,
                    0.43476203083992004,
                    0.34971052408218384
                ]
            ],
            "right_EE_pose": [
                [
                    -1.6751118898391724,
                    0.6474340558052063,
                    0.9438145160675049
                ],
                [
                    0.2222396433353424,
                    0.8243006467819214,
                    -0.15674874186515808,
                    -0.49655595421791077
                ]
            ]
        },
        {
            "left_EE_pose": [
                [
                    -1.62916898727417,
                    -0.3209005296230316,
                    0.9483967423439026
                ],
                [
                    -0.3951766788959503,
                    -0.7293285727500916,
                    0.43523073196411133,
                    0.34998488426208496
                ]
            ],
            "right_EE_pose": [
                [
                    -1.6761201620101929,
                    0.6479268670082092,
                    0.9426464438438416
                ],
                [
                    0.22125136852264404,
                    0.8240359425544739,
                    -0.15831789374351501,
                    -0.49693864583969116
                ]
            ]
        },
        {
            "left_EE_pose": [
                [
                    -1.627398133277893,
                    -0.3196854889392853,
                    0.9483770728111267
                ],
                [
                    -0.39547786116600037,
                    -0.728188157081604,
                    0.4368690550327301,
                    0.34997814893722534
                ]
            ],
            "right_EE_pose": [
                [
                    -1.6770846843719482,
                    0.6487213373184204,
                    0.9412826299667358
                ],
                [
                    0.22014784812927246,
                    0.8238878846168518,
                    -0.16010929644107819,
                    -0.497100293636322
                ]
            ]
        },
        {
            "left_EE_pose": [
                [
                    -1.6258833408355713,
                    -0.3186642527580261,
                    0.9484580159187317
                ],
                [
                    -0.39440426230430603,
                    -0.7277799844741821,
                    0.4391070008277893,
                    0.34923720359802246
                ]
            ],
            "right_EE_pose": [
                [
                    -1.6781344413757324,
                    0.6493668556213379,
                    0.9399355053901672
                ],
                [
                    0.218598410487175,
                    0.8230640292167664,
                    -0.16222664713859558,
                    -0.4984605014324188
                ]
            ]
        },
        {
            "left_EE_pose": [
                [
                    -1.6247929334640503,
                    -0.3178725242614746,
                    0.9484267234802246
                ],
                [
                    -0.3935984969139099,
                    -0.7277735471725464,
                    0.4398365616798401,
                    0.3492416441440582
                ]
            ],
            "right_EE_pose": [
                [
                    -1.6787782907485962,
                    0.6498859524726868,
                    0.9390329122543335
                ],
                [
                    0.21838438510894775,
                    0.822975754737854,
                    -0.1633801907300949,
                    -0.4983232617378235
                ]
            ]
        },
        {
            "left_EE_pose": [
                [
                    -1.6247929334640503,
                    -0.3178725242614746,
                    0.9484267234802246
                ],
                [
                    -0.3935984969139099,
                    -0.7277735471725464,
                    0.4398365616798401,
                    0.3492416441440582
                ]
            ],
            "right_EE_pose": [
                [
                    -1.6787782907485962,
                    0.6498859524726868,
                    0.9390329122543335
                ],
                [
                    0.21838438510894775,
                    0.822975754737854,
                    -0.1633801907300949,
                    -0.4983232617378235
                ]
            ]
        },
        {
            "left_EE_pose": [
                [
                    -1.6225730180740356,
                    -0.3163895905017853,
                    0.9486172199249268
                ],
                [
                    -0.39236974716186523,
                    -0.7267313003540039,
                    0.4423844814300537,
                    0.34957626461982727
                ]
            ],
            "right_EE_pose": [
                [
                    -1.680184245109558,
                    0.6508694887161255,
                    0.9371805787086487
                ],
                [
                    0.21696580946445465,
                    0.8225627541542053,
                    -0.16577982902526855,
                    -0.4988320469856262
                ]
            ]
        },
        {
            "left_EE_pose": [
                [
                    -1.6214834451675415,
                    -0.31571704149246216,
                    0.9486904144287109
                ],
                [
                    -0.39202681183815,
                    -0.7268195748329163,
                    0.44262072443962097,
                    0.34947842359542847
                ]
            ],
            "right_EE_pose": [
                [
                    -1.6807799339294434,
                    0.6513094902038574,
                    0.9363043904304504
                ],
                [
                    0.21639162302017212,
                    0.8220513463020325,
                    -0.16656573116779327,
                    -0.49966201186180115
                ]
            ]
        },
        {
            "left_EE_pose": [
                [
                    -1.6190097332000732,
                    -0.31415605545043945,
                    0.9487006068229675
                ],
                [
                    -0.3903910517692566,
                    -0.7260761857032776,
                    0.4455079734325409,
                    0.349185973405838
                ]
            ],
            "right_EE_pose": [
                [
                    -1.6821057796478271,
                    0.6525302529335022,
                    0.9343146681785583
                ],
                [
                    0.21478013694286346,
                    0.8213196396827698,
                    -0.16922453045845032,
                    -0.5006662607192993
                ]
            ]
        },
        {
            "left_EE_pose": [
                [
                    -1.6176319122314453,
                    -0.31334394216537476,
                    0.9487985968589783
                ],
                [
                    -0.3895139992237091,
                    -0.7257552742958069,
                    0.44675198197364807,
                    0.3492431342601776
                ]
            ],
            "right_EE_pose": [
                [
                    -1.6829723119735718,
                    0.6532230973243713,
                    0.9331740140914917
                ],
                [
                    0.21395409107208252,
                    0.8209887146949768,
                    -0.1709485948085785,
                    -0.5009767413139343
                ]
            ]
        },
        {
            "left_EE_pose": [
                [
                    -1.6153678894042969,
                    -0.31184786558151245,
                    0.9489142298698425
                ],
                [
                    -0.3883911073207855,
                    -0.7252850532531738,
                    0.44839566946029663,
                    0.3493640422821045
                ]
            ],
            "right_EE_pose": [
                [
                    -1.68412446975708,
                    0.6543102264404297,
                    0.931441605091095
                ],
                [
                    0.21333366632461548,
                    0.819739043712616,
                    -0.17354461550712585,
                    -0.5023931264877319
                ]
            ]
        },
        {
            "left_EE_pose": [
                [
                    -1.6141443252563477,
                    -0.3109925389289856,
                    0.9489222168922424
                ],
                [
                    -0.386314332485199,
                    -0.7251720428466797,
                    0.4502660632133484,
                    0.34949561953544617
                ]
            ],
            "right_EE_pose": [
                [
                    -1.6848665475845337,
                    0.6550356149673462,
                    0.9302860498428345
                ],
                [
                    0.21271976828575134,
                    0.8197129964828491,
                    -0.1745540052652359,
                    -0.5023462772369385
                ]
            ]
        },
        {
            "left_EE_pose": [
                [
                    -1.6127283573150635,
                    -0.31017032265663147,
                    0.9489505290985107
                ],
                [
                    -0.3859409689903259,
                    -0.724682092666626,
                    0.4514595866203308,
                    0.34938469529151917
                ]
            ],
            "right_EE_pose": [
                [
                    -1.6854932308197021,
                    0.6557617783546448,
                    0.9291712045669556
                ],
                [
                    0.21124596893787384,
                    0.8189414739608765,
                    -0.17566359043121338,
                    -0.503837525844574
                ]
            ]
        },
        {
            "left_EE_pose": [
                [
                    -1.6111674308776855,
                    -0.30919715762138367,
                    0.9490311145782471
                ],
                [
                    -0.38440200686454773,
                    -0.724204421043396,
                    0.45330581068992615,
                    0.3496811091899872
                ]
            ],
            "right_EE_pose": [
                [
                    -1.6863981485366821,
                    0.6566296815872192,
                    0.9278541803359985
                ],
                [
                    0.21070365607738495,
                    0.8182766437530518,
                    -0.17800669372081757,
                    -0.5043224096298218
                ]
            ]
        },
        {
            "left_EE_pose": [
                [
                    -1.6095370054244995,
                    -0.3082684278488159,
                    0.9491081833839417
                ],
                [
                    -0.38178467750549316,
                    -0.7241373062133789,
                    0.45570099353790283,
                    0.34957438707351685
                ]
            ],
            "right_EE_pose": [
                [
                    -1.687125563621521,
                    0.6574834585189819,
                    0.9265141487121582
                ],
                [
                    0.20986409485340118,
                    0.8177024126052856,
                    -0.17958644032478333,
                    -0.5050431489944458
                ]
            ]
        },
        {
            "left_EE_pose": [
                [
                    -1.6090236902236938,
                    -0.3079153001308441,
                    0.9491273164749146
                ],
                [
                    -0.3807930052280426,
                    -0.7241698503494263,
                    0.45582443475723267,
                    0.35042670369148254
                ]
            ],
            "right_EE_pose": [
                [
                    -1.6873600482940674,
                    0.6578292846679688,
                    0.9260215759277344
                ],
                [
                    0.2097378820180893,
                    0.8172566890716553,
                    -0.17999759316444397,
                    -0.5056702494621277
                ]
            ]
        },
        {
            "left_EE_pose": [
                [
                    -1.6059788465499878,
                    -0.30624547600746155,
                    0.9492387175559998
                ],
                [
                    -0.37895336747169495,
                    -0.7232213616371155,
                    0.4586024582386017,
                    0.35075485706329346
                ]
            ],
            "right_EE_pose": [
                [
                    -1.6887688636779785,
                    0.6596162915229797,
                    0.9236588478088379
                ],
                [
                    0.20876595377922058,
                    0.8152977228164673,
                    -0.18268683552742004,
                    -0.5082635879516602
                ]
            ]
        },
        {
            "left_EE_pose": [
                [
                    -1.603835940361023,
                    -0.30502933263778687,
                    0.9491643309593201
                ],
                [
                    -0.37589746713638306,
                    -0.7228694558143616,
                    0.46112608909606934,
                    0.351459264755249
                ]
            ],
            "right_EE_pose": [
                [
                    -1.6897019147872925,
                    0.6608561277389526,
                    0.9218621850013733
                ],
                [
                    0.20760147273540497,
                    0.8145621418952942,
                    -0.18464034795761108,
                    -0.5092131495475769
                ]
            ]
        },
        {
            "left_EE_pose": [
                [
                    -1.6025192737579346,
                    -0.30416226387023926,
                    0.9491892457008362
                ],
                [
                    -0.3739132285118103,
                    -0.7220773696899414,
                    0.46435755491256714,
                    0.3509490489959717
                ]
            ],
            "right_EE_pose": [
                [
                    -1.690226674079895,
                    0.6615968942642212,
                    0.920847475528717
                ],
                [
                    0.20701591670513153,
                    0.8138290047645569,
                    -0.18610624969005585,
                    -0.5100895762443542
                ]
            ]
        },
        {
            "left_EE_pose": [
                [
                    -1.6013081073760986,
                    -0.30361542105674744,
                    0.9492329359054565
                ],
                [
                    -0.37350040674209595,
                    -0.7219138145446777,
                    0.46458977460861206,
                    0.3514174818992615
                ]
            ],
            "right_EE_pose": [
                [
                    -1.6906969547271729,
                    0.6623445749282837,
                    0.9200068116188049
                ],
                [
                    0.20679347217082977,
                    0.8126413822174072,
                    -0.1873006671667099,
                    -0.511633574962616
                ]
            ]
        },
        {
            "left_EE_pose": [
                [
                    -1.6008228063583374,
                    -0.30335795879364014,
                    0.949202299118042
                ],
                [
                    -0.37297871708869934,
                    -0.7220268845558167,
                    0.46510711312294006,
                    0.35105472803115845
                ]
            ],
            "right_EE_pose": [
                [
                    -1.6909565925598145,
                    0.6626755595207214,
                    0.919522762298584
                ],
                [
                    0.20681440830230713,
                    0.8127279281616211,
                    -0.18796497583389282,
                    -0.5112438201904297
                ]
            ]
        },
        {
            "left_EE_pose": [
                [
                    -1.5994820594787598,
                    -0.3026283085346222,
                    0.9493588209152222
                ],
                [
                    -0.3713408410549164,
                    -0.7217333316802979,
                    0.46636345982551575,
                    0.35172727704048157
                ]
            ],
            "right_EE_pose": [
                [
                    -1.6915066242218018,
                    0.6634425520896912,
                    0.9184097647666931
                ],
                [
                    0.20596814155578613,
                    0.8121191263198853,
                    -0.18893572688102722,
                    -0.5121942758560181
                ]
            ]
        },
        {
            "left_EE_pose": [
                [
                    -1.598629355430603,
                    -0.30225542187690735,
                    0.9494238495826721
                ],
                [
                    -0.37025538086891174,
                    -0.7217414975166321,
                    0.46694865822792053,
                    0.35207828879356384
                ]
            ],
            "right_EE_pose": [
                [
                    -1.6917651891708374,
                    0.6640586853027344,
                    0.9177821278572083
                ],
                [
                    0.20601412653923035,
                    0.8117612600326538,
                    -0.1894076019525528,
                    -0.5125687122344971
                ]
            ]
        },
        {
            "left_EE_pose": [
                [
                    -1.5965152978897095,
                    -0.3010300099849701,
                    0.9493476748466492
                ],
                [
                    -0.3661041259765625,
                    -0.7210491299629211,
                    0.47080132365226746,
                    0.3527069687843323
                ]
            ],
            "right_EE_pose": [
                [
                    -1.692618489265442,
                    0.6654255390167236,
                    0.9160357713699341
                ],
                [
                    0.20594540238380432,
                    0.8101015686988831,
                    -0.1913428157567978,
                    -0.5144996643066406
                ]
            ]
        },
        {
            "left_EE_pose": [
                [
                    -1.5955535173416138,
                    -0.3004324734210968,
                    0.9492986798286438
                ],
                [
                    -0.36457395553588867,
                    -0.720923900604248,
                    0.4721366763114929,
                    0.3527626693248749
                ]
            ],
            "right_EE_pose": [
                [
                    -1.6930198669433594,
                    0.6661792397499084,
                    0.9151468276977539
                ],
                [
                    0.20530544221401215,
                    0.8096245527267456,
                    -0.19237424433231354,
                    -0.5151214003562927
                ]
            ]
        },
        {
            "left_EE_pose": [
                [
                    -1.594963788986206,
                    -0.30019980669021606,
                    0.9493276476860046
                ],
                [
                    -0.36362895369529724,
                    -0.720690906047821,
                    0.4730275869369507,
                    0.3530205488204956
                ]
            ],
            "right_EE_pose": [
                [
                    -1.6932110786437988,
                    0.6665383577346802,
                    0.9147500395774841
                ],
                [
                    0.20505134761333466,
                    0.8093624114990234,
                    -0.1928255558013916,
                    -0.515465497970581
                ]
            ]
        },
        {
            "left_EE_pose": [
                [
                    -1.594340443611145,
                    -0.29988032579421997,
                    0.9493371248245239
                ],
                [
                    -0.36285459995269775,
                    -0.7202383279800415,
                    0.47369590401649475,
                    0.35384392738342285
                ]
            ],
            "right_EE_pose": [
                [
                    -1.6933484077453613,
                    0.6668902039527893,
                    0.914322555065155
                ],
                [
                    0.20477958023548126,
                    0.8086680173873901,
                    -0.19345860183238983,
                    -0.516425371170044
                ]
            ]
        },
        {
            "left_EE_pose": [
                [
                    -1.5930379629135132,
                    -0.2992439866065979,
                    0.9492971301078796
                ],
                [
                    -0.3613203763961792,
                    -0.7199838161468506,
                    0.4753184914588928,
                    0.3537560999393463
                ]
            ],
            "right_EE_pose": [
                [
                    -1.6937744617462158,
                    0.6677700281143188,
                    0.913311243057251
                ],
                [
                    0.20434391498565674,
                    0.8077807426452637,
                    -0.1942324936389923,
                    -0.5176945924758911
                ]
            ]
        },
        {
            "left_EE_pose": [
                [
                    -1.5925006866455078,
                    -0.29893314838409424,
                    0.9493020176887512
                ],
                [
                    -0.3601126968860626,
                    -0.7201337218284607,
                    0.47604987025260925,
                    0.3536987900733948
                ]
            ],
            "right_EE_pose": [
                [
                    -1.6939001083374023,
                    0.6681551933288574,
                    0.9128538966178894
                ],
                [
                    0.2047921121120453,
                    0.8072059750556946,
                    -0.194448322057724,
                    -0.5183324813842773
                ]
            ]
        },
        {
            "left_EE_pose": [
                [
                    -1.591247320175171,
                    -0.2981749176979065,
                    0.9492420554161072
                ],
                [
                    -0.35713517665863037,
                    -0.7197960019111633,
                    0.47887182235717773,
                    0.3535957932472229
                ]
            ],
            "right_EE_pose": [
                [
                    -1.694358229637146,
                    0.6690877079963684,
                    0.9117257595062256
                ],
                [
                    0.2043723315000534,
                    0.8068193197250366,
                    -0.1957464963197708,
                    -0.5186113715171814
                ]
            ]
        },
        {
            "left_EE_pose": [
                [
                    -1.5909602642059326,
                    -0.2980387210845947,
                    0.9492288827896118
                ],
                [
                    -0.356574147939682,
                    -0.7196006774902344,
                    0.479402631521225,
                    0.3538402020931244
                ]
            ],
            "right_EE_pose": [
                [
                    -1.6944220066070557,
                    0.6692960858345032,
                    0.9115539789199829
                ],
                [
                    0.20431260764598846,
                    0.8064758777618408,
                    -0.19598454236984253,
                    -0.5190791487693787
                ]
            ]
        },
        {
            "left_EE_pose": [
                [
                    -1.589004635810852,
                    -0.2971806824207306,
                    0.9493095874786377
                ],
                [
                    -0.3553636372089386,
                    -0.7190434336662292,
                    0.48030462861061096,
                    0.3549657464027405
                ]
            ],
            "right_EE_pose": [
                [
                    -1.6950210332870483,
                    0.6705602407455444,
                    0.9100666642189026
                ],
                [
                    0.20392203330993652,
                    0.8054862022399902,
                    -0.19736765325069427,
                    -0.5202439427375793
                ]
            ]
        },
        {
            "left_EE_pose": [
                [
                    -1.5881638526916504,
                    -0.2967189848423004,
                    0.9493424892425537
                ],
                [
                    -0.353446364402771,
                    -0.7187374830245972,
                    0.48208853602409363,
                    0.3550812602043152
                ]
            ],
            "right_EE_pose": [
                [
                    -1.6952874660491943,
                    0.671142041683197,
                    0.9094458222389221
                ],
                [
                    0.2043626457452774,
                    0.8048757314682007,
                    -0.19739434123039246,
                    -0.5210052132606506
                ]
            ]
        },
        {
            "left_EE_pose": [
                [
                    -1.587377905845642,
                    -0.2962689697742462,
                    0.9493341445922852
                ],
                [
                    -0.3518257737159729,
                    -0.7186861634254456,
                    0.4829081892967224,
                    0.35568034648895264
                ]
            ],
            "right_EE_pose": [
                [
                    -1.6954718828201294,
                    0.6716997027397156,
                    0.9088174104690552
                ],
                [
                    0.2043963521718979,
                    0.8038623332977295,
                    -0.19824524223804474,
                    -0.5222321152687073
                ]
            ]
        },
        {
            "left_EE_pose": [
                [
                    -1.5860978364944458,
                    -0.2955958843231201,
                    0.9492140412330627
                ],
                [
                    -0.34804895520210266,
                    -0.718612551689148,
                    0.4852687120437622,
                    0.35633155703544617
                ]
            ],
            "right_EE_pose": [
                [
                    -1.695841908454895,
                    0.6727522611618042,
                    0.9077687859535217
                ],
                [
                    0.2039928287267685,
                    0.8024897575378418,
                    -0.19902145862579346,
                    -0.5242018103599548
                ]
            ]
        },
        {
            "left_EE_pose": [
                [
                    -1.5844874382019043,
                    -0.2948593497276306,
                    0.9492334723472595
                ],
                [
                    -0.3449391722679138,
                    -0.7179639339447021,
                    0.4877302944660187,
                    0.3573010265827179
                ]
            ],
            "right_EE_pose": [
                [
                    -1.6961778402328491,
                    0.6738033890724182,
                    0.906575083732605
                ],
                [
                    0.20295743644237518,
                    0.801266610622406,
                    -0.2004248946905136,
                    -0.5259371995925903
                ]
            ]
        },
        {
            "left_EE_pose": [
                [
                    -1.5834983587265015,
                    -0.29448801279067993,
                    0.9492589831352234
                ],
                [
                    -0.3453667163848877,
                    -0.7178817987442017,
                    0.4871273934841156,
                    0.35787490010261536
                ]
            ],
            "right_EE_pose": [
                [
                    -1.696380853652954,
                    0.6744035482406616,
                    0.9059575200080872
                ],
                [
                    0.20317226648330688,
                    0.8008242845535278,
                    -0.20083296298980713,
                    -0.5263721346855164
                ]
            ]
        },
        {
            "left_EE_pose": [
                [
                    -1.5825581550598145,
                    -0.29395565390586853,
                    0.9492658972740173
                ],
                [
                    -0.3435531556606293,
                    -0.7176942825317383,
                    0.48900100588798523,
                    0.35744133591651917
                ]
            ],
            "right_EE_pose": [
                [
                    -1.6966553926467896,
                    0.6752790808677673,
                    0.9051035046577454
                ],
                [
                    0.20324921607971191,
                    0.8002371191978455,
                    -0.2013244479894638,
                    -0.527047336101532
                ]
            ]
        },
        {
            "left_EE_pose": [
                [
                    -1.58151376247406,
                    -0.2934948801994324,
                    0.9492022395133972
                ],
                [
                    -0.34087860584259033,
                    -0.717654287815094,
                    0.49056583642959595,
                    0.3579375147819519
                ]
            ],
            "right_EE_pose": [
                [
                    -1.6969045400619507,
                    0.6761013269424438,
                    0.9043093919754028
                ],
                [
                    0.20301905274391174,
                    0.7989668250083923,
                    -0.20202665030956268,
                    -0.528791606426239
                ]
            ]
        },
        {
            "left_EE_pose": [
                [
                    -1.5801433324813843,
                    -0.2923736870288849,
                    0.9493511915206909
                ],
                [
                    -0.33845195174217224,
                    -0.7169005274772644,
                    0.493585467338562,
                    0.35759955644607544
                ]
            ],
            "right_EE_pose": [
                [
                    -1.6980199813842773,
                    0.6766863465309143,
                    0.903322696685791
                ],
                [
                    0.20197570323944092,
                    0.7984511852264404,
                    -0.20371432602405548,
                    -0.5293222665786743
                ]
            ]
        },
        {
            "left_EE_pose": [
                [
                    -1.579899549484253,
                    -0.29213133454322815,
                    0.9494099617004395
                ],
                [
                    -0.3381722569465637,
                    -0.7168424725532532,
                    0.49412938952445984,
                    0.35722896456718445
                ]
            ],
            "right_EE_pose": [
                [
                    -1.698126196861267,
                    0.676802933216095,
                    0.9031242728233337
                ],
                [
                    0.20181585848331451,
                    0.798261284828186,
                    -0.2040887176990509,
                    -0.5295253396034241
                ]
            ]
        }
    ],
    "metadata": {
        "reference_right_from_left": [
            [
                -0.5306423902511597,
                -0.821404755115509,
                -0.017984449863433838
            ],
            [
                0.13915032148361206,
                -0.12203481048345566,
                0.3121871054172516,
                0.9318175315856934
            ]
        ]
    }
}